{
    "qef_simple_location_rules": 0,
    "key": "group_654e6608aca86",
    "title": "Block - Posts Grid",
    "fields": [
        {
            "allow_backendsearch": false,
            "show_column_filter": false,
            "allow_bulkedit": false,
            "allow_quickedit": false,
            "show_column": false,
            "show_column_weight": 1000,
            "show_column_sortable": false,
            "key": "field_654e6609f28f1",
            "label": "Number of Posts",
            "name": "number_of_posts",
            "aria-label": "",
            "type": "number",
            "instructions": "",
            "required": 0,
            "conditional_logic": 0,
            "wrapper": {
                "width": "",
                "class": "",
                "id": ""
            },
            "default_value": 6,
            "min": 3,
            "max": "",
            "placeholder": "",
            "step": 1,
            "prepend": "",
            "append": ""
        },
        {
            "allow_backendsearch": false,
            "show_column_filter": 0,
            "allow_bulkedit": 0,
            "allow_quickedit": 0,
            "show_column": 0,
            "show_column_weight": 1000,
            "show_column_sortable": false,
            "key": "field_654e662cf28f2",
            "label": "Columns",
            "name": "columns",
            "aria-label": "",
            "type": "button_group",
            "instructions": "",
            "required": 0,
            "conditional_logic": 0,
            "wrapper": {
                "width": "",
                "class": "",
                "id": ""
            },
            "choices": {
                "2": "2",
                "3": "3",
                "4": "4"
            },
            "default_value": 3,
            "return_format": "value",
            "allow_null": 0,
            "layout": "horizontal"
        },
        {
            "allow_backendsearch": false,
            "show_column_filter": false,
            "allow_bulkedit": false,
            "allow_quickedit": false,
            "show_column": false,
            "show_column_weight": 1000,
            "show_column_sortable": false,
            "key": "field_654e6cac23338",
            "label": "Column Gap",
            "name": "column_gap",
            "aria-label": "",
            "type": "button_group",
            "instructions": "",
            "required": 0,
            "conditional_logic": 0,
            "wrapper": {
                "width": "",
                "class": "",
                "id": ""
            },
            "choices": {
                "none": "None",
                "xs": "XS",
                "sm": "SM",
                "md": "MD",
                "lg": "LG",
                "xl": "XL"
            },
            "default_value": "md",
            "return_format": "value",
            "allow_null": 0,
            "layout": "horizontal"
        },
        {
            "allow_backendsearch": false,
            "show_column_filter": false,
            "allow_bulkedit": false,
            "allow_quickedit": false,
            "show_column": false,
            "show_column_weight": 1000,
            "show_column_sortable": false,
            "key": "field_654e67d8705ea",
            "label": "Category",
            "name": "category",
            "aria-label": "",
            "type": "taxonomy",
            "instructions": "",
            "required": 0,
            "conditional_logic": 0,
            "wrapper": {
                "width": "",
                "class": "",
                "id": ""
            },
            "taxonomy": "category",
            "add_term": 0,
            "save_terms": 0,
            "load_terms": 1,
            "return_format": "id",
            "field_type": "checkbox",
            "bidirectional": 0,
            "multiple": 0,
            "allow_null": 0,
            "bidirectional_target": []
        }
    ],
    "location": [
        [
            {
                "param": "block",
                "operator": "==",
                "value": "acf\/posts-grid"
            }
        ]
    ],
    "menu_order": 0,
    "position": "normal",
    "style": "default",
    "label_placement": "top",
    "instruction_placement": "label",
    "hide_on_screen": "",
    "active": true,
    "description": "",
    "show_in_rest": 0,
    "modified": 1699660246
}
